pydantic_neuroglancer/__init__.py
pydantic_neuroglancer/cli.py
pydantic_neuroglancer/url_state.py
pydantic_neuroglancer/viewer_state.py
pydantic_neuroglancer-0.2.0.dist-info/METADATA
pydantic_neuroglancer-0.2.0.dist-info/WHEEL
pydantic_neuroglancer-0.2.0.dist-info/RECORD
