Metadata-Version: 2.1
Name: pydantic-neuroglancer
Version: 0.2.0
Summary: Pydantic models for neuroglancer viewer state
License: BSD 3-clause
Author: Davis Vann Bennett
Author-email: davis.v.bennett@gmail.com
Requires-Python: >=3.9,<4
Classifier: License :: Other/Proprietary License
Classifier: Programming Language :: Python :: 3
Classifier: Programming Language :: Python :: 3.9
Classifier: Programming Language :: Python :: 3.10
Classifier: Programming Language :: Python :: 3.11
Requires-Dist: click (>=8.1.3,<9.0.0)
Requires-Dist: pydantic (>=1.9.0,<2.0.0)
